precovery-1.0.0.dist-info/METADATA
precovery-1.0.0.dist-info/WHEEL
precovery-1.0.0.dist-info/entry_points.txt
precovery-1.0.0.dist-info/licenses/LICENSE.md
precovery/__init__.py
precovery/__pycache__/spherical_geom.haversine_distance-5.py310.1.nbc
precovery/__pycache__/spherical_geom.haversine_distance-5.py310.2.nbc
precovery/__pycache__/spherical_geom.haversine_distance-5.py310.3.nbc
precovery/__pycache__/spherical_geom.haversine_distance-5.py310.4.nbc
precovery/__pycache__/spherical_geom.haversine_distance-5.py310.5.nbc
precovery/__pycache__/spherical_geom.haversine_distance-5.py310.6.nbc
precovery/__pycache__/spherical_geom.haversine_distance-5.py310.7.nbc
precovery/__pycache__/spherical_geom.haversine_distance-5.py310.8.nbc
precovery/__pycache__/spherical_geom.haversine_distance-5.py310.9.nbc
precovery/__pycache__/spherical_geom.haversine_distance-5.py310.nbi
precovery/__pycache__/spherical_geom.haversine_distance-5.py311.1.nbc
precovery/__pycache__/spherical_geom.haversine_distance-5.py311.2.nbc
precovery/__pycache__/spherical_geom.haversine_distance-5.py311.3.nbc
precovery/__pycache__/spherical_geom.haversine_distance-5.py311.4.nbc
precovery/__pycache__/spherical_geom.haversine_distance-5.py311.nbi
precovery/__pycache__/spherical_geom.haversine_distance-60.py310.1.nbc
precovery/__pycache__/spherical_geom.haversine_distance-60.py310.nbi
precovery/__pycache__/spherical_geom.haversine_distance_deg-17.py310.1.nbc
precovery/__pycache__/spherical_geom.haversine_distance_deg-17.py310.10.nbc
precovery/__pycache__/spherical_geom.haversine_distance_deg-17.py310.11.nbc
precovery/__pycache__/spherical_geom.haversine_distance_deg-17.py310.12.nbc
precovery/__pycache__/spherical_geom.haversine_distance_deg-17.py310.13.nbc
precovery/__pycache__/spherical_geom.haversine_distance_deg-17.py310.14.nbc
precovery/__pycache__/spherical_geom.haversine_distance_deg-17.py310.2.nbc
precovery/__pycache__/spherical_geom.haversine_distance_deg-17.py310.3.nbc
precovery/__pycache__/spherical_geom.haversine_distance_deg-17.py310.4.nbc
precovery/__pycache__/spherical_geom.haversine_distance_deg-17.py310.5.nbc
precovery-1.0.0.dist-info/RECORD
