Metadata-Version: 2.1
Name: precovery
Version: 1.0.0
Summary: Fast asteroid precovery at scale
Author-Email: Kathleen Kiker <kathleen@b612foundation.org>, Alec Koumjian <alec@b612foundation.org>, Joachim Moeyens <moeyensj@uw.edu>, Spencer Nelson <spencer@b612foundation.org>, Nate Tellis <nate@b612foundation.org>
License: BSD 3-Clause License
Classifier: Development Status :: 3 - Alpha
Classifier: Intended Audience :: Science/Research
Classifier: License :: OSI Approved :: BSD License
Classifier: Operating System :: OS Independent
Classifier: Programming Language :: Python :: 3.10
Classifier: Programming Language :: Python :: 3.11
Classifier: Topic :: Scientific/Engineering :: Astronomy
Classifier: Topic :: Scientific/Engineering :: Physics
Project-URL: Homepage, https://github.com/b612-asteroid-institute/precovery
Requires-Python: <3.13,>=3.11
Requires-Dist: numpy
Requires-Dist: numba
Requires-Dist: sqlalchemy
Requires-Dist: regex
Requires-Dist: pandas
Requires-Dist: healpy
Requires-Dist: requests
Requires-Dist: adam-core>=0.3.1
